port_for/__init__.py
port_for/_download_ranges.py
port_for/_ranges.py
port_for/api.py
port_for/cmd.py
port_for/docopt.py
port_for/ephemeral.py
port_for/exceptions.py
port_for/py.typed
port_for/store.py
port_for/utils.py
port_for-0.7.1.dist-info/LICENSE.txt
port_for-0.7.1.dist-info/METADATA
port_for-0.7.1.dist-info/WHEEL
port_for-0.7.1.dist-info/entry_points.txt
port_for-0.7.1.dist-info/top_level.txt
port_for-0.7.1.dist-info/zip-safe
port_for-0.7.1.dist-info/RECORD
