Metadata-Version: 2.1
Name: port-for
Version: 0.7.1
Summary: Utility that helps with local TCP ports management. It can find an unused TCP localhost port and remember the association.
Author-email: Mikhail Korobov <kmike84@gmail.com>
Maintainer-email: Grzegorz Śliwiński <fizyk+pypi@fizyk.dev>
License: Copyright (c) 2012 Mikhail Korobov
Project-URL: Source, https://github.com/kmike/port-for/
Project-URL: Bug Tracker, https://github.com/kmike/port-for/issues
Project-URL: Changelog, https://github.com/kmike/port-for/blob/v0.7.1/CHANGES.rst
Keywords: port,posix
Classifier: Development Status :: 4 - Beta
Classifier: Intended Audience :: Developers
Classifier: Intended Audience :: System Administrators
Classifier: License :: OSI Approved :: MIT License
Classifier: Programming Language :: Python
Classifier: Programming Language :: Python :: 3
Classifier: Programming Language :: Python :: 3.7
Classifier: Programming Language :: Python :: 3.8
Classifier: Programming Language :: Python :: 3.9
Classifier: Programming Language :: Python :: 3.10
Classifier: Programming Language :: Python :: 3.11
Classifier: Operating System :: POSIX
Classifier: Topic :: System :: Installation/Setup
Classifier: Topic :: System :: Systems Administration
Classifier: Topic :: Internet :: WWW/HTTP :: Site Management
Requires-Python: >=3.7
License-File: LICENSE.txt
